swiftscrub/__init__.py
swiftscrub/llm.py
swiftscrub/py.typed
swiftscrub/anonymization/__init__.py
swiftscrub/anonymization/anonymize.py
swiftscrub/anonymization/core.py
swiftscrub/anonymization/cvs.py
swiftscrub/anonymization/prompts.py
swiftscrub/pseudonymization/__init__.py
swiftscrub/pseudonymization/bert_recognizer.py
swiftscrub/pseudonymization/core.py
swiftscrub/pseudonymization/instance_counter.py
swiftscrub-0.1.2.dist-info/METADATA
swiftscrub-0.1.2.dist-info/WHEEL
swiftscrub-0.1.2.dist-info/licenses/LICENSE
swiftscrub-0.1.2.dist-info/RECORD
