Metadata-Version: 2.4
Name: swiftscrub
Version: 0.1.2
Summary: A framework for anonymizing and scrubbing sensitive data from text.
Author-email: Prannaya Gupta <prannayagupta@gmail.com>
License-File: LICENSE
Requires-Python: >=3.9
Requires-Dist: presidio-analyzer>=2.2.358
Requires-Dist: presidio-anonymizer>=2.2.358
Requires-Dist: sentence-transformers>=4.1.0
Requires-Dist: sentencex>=0.6.1
Requires-Dist: torch>=2.7.0
Requires-Dist: transformers>=4.52.4
